pyrithmic/main.py
pyrithmic-0.1.0.dist-info/METADATA
pyrithmic-0.1.0.dist-info/WHEEL
pyrithmic-0.1.0.dist-info/RECORD
