Metadata-Version: 2.1
Name: pyrithmic
Version: 0.1.0
Summary: A lightweight python wrapper for Rithmic's C++ API
Author: Daniel Bond
Author-email: daniel.bond01@outlook.com
Requires-Python: >=3.8,<4.0
Classifier: Programming Language :: Python :: 3
Classifier: Programming Language :: Python :: 3.8
Classifier: Programming Language :: Python :: 3.9
Classifier: Programming Language :: Python :: 3.10
Classifier: Programming Language :: Python :: 3.11
